odoo/addons/product_configurator_restriction_policy/README.rst
odoo/addons/product_configurator_restriction_policy/__init__.py
odoo/addons/product_configurator_restriction_policy/__manifest__.py
odoo/addons/product_configurator_restriction_policy/i18n/it.po
odoo/addons/product_configurator_restriction_policy/i18n/product_configurator_restriction_policy.pot
odoo/addons/product_configurator_restriction_policy/models/__init__.py
odoo/addons/product_configurator_restriction_policy/models/product.py
odoo/addons/product_configurator_restriction_policy/models/product_config.py
odoo/addons/product_configurator_restriction_policy/models/res_config_settings.py
odoo/addons/product_configurator_restriction_policy/readme/DESCRIPTION.rst
odoo/addons/product_configurator_restriction_policy/readme/USAGE.rst
odoo/addons/product_configurator_restriction_policy/static/description/icon.png
odoo/addons/product_configurator_restriction_policy/static/description/index.html
odoo/addons/product_configurator_restriction_policy/views/product_view.xml
odoo/addons/product_configurator_restriction_policy/views/res_config_settings_view.xml
odoo14_addon_product_configurator_restriction_policy-14.0.1.0.1.dev5.dist-info/METADATA
odoo14_addon_product_configurator_restriction_policy-14.0.1.0.1.dev5.dist-info/WHEEL
odoo14_addon_product_configurator_restriction_policy-14.0.1.0.1.dev5.dist-info/top_level.txt
odoo14_addon_product_configurator_restriction_policy-14.0.1.0.1.dev5.dist-info/RECORD
