Metadata-Version: 2.1
Name: odoo14-addon-product_configurator_restriction_policy
Version: 14.0.1.0.1.dev5
Summary: Adds a Restriction Policy for processing restrictions.
Home-page: https://github.com/OCA/product-configurator
Author: Open Source Integrators, Odoo Community Association (OCA)
Author-email: support@odoo-community.org
License: AGPL-3
Classifier: Programming Language :: Python
Classifier: Framework :: Odoo
Classifier: Framework :: Odoo :: 14.0
Classifier: License :: OSI Approved :: GNU Affero General Public License v3
Classifier: Development Status :: 4 - Beta
Requires-Python: >=3.6
Requires-Dist: odoo14-addon-product-configurator
Requires-Dist: odoo<14.1dev,>=14.0a
